amrkt/__init__.py
amrkt/client.py
amrkt/exceptions.py
amrkt/models.py
amrkt/py.typed
amrkt-1.0.0.dist-info/METADATA
amrkt-1.0.0.dist-info/WHEEL
amrkt-1.0.0.dist-info/licenses/LICENSE
amrkt-1.0.0.dist-info/RECORD
