Metadata-Version: 2.4
Name: amrkt
Version: 1.0.0
Summary: Async Python library for mrkt
Project-URL: Homepage, https://github.com/thebrainair/amrkt
Project-URL: Documentation, https://github.com/thebrainair/amrkt#readme
Project-URL: Repository, https://github.com/thebrainair/amrkt
Project-URL: Issues, https://github.com/thebrainair/amrkt/issues
Author: thebrainair
License: MIT
License-File: LICENSE
Keywords: api,async,gifts,market,nft,telegram,tgmrkt
Classifier: Development Status :: 4 - Beta
Classifier: Framework :: AsyncIO
Classifier: Intended Audience :: Developers
Classifier: License :: OSI Approved :: MIT License
Classifier: Operating System :: OS Independent
Classifier: Programming Language :: Python :: 3
Classifier: Programming Language :: Python :: 3.9
Classifier: Programming Language :: Python :: 3.10
Classifier: Programming Language :: Python :: 3.11
Classifier: Programming Language :: Python :: 3.12
Classifier: Programming Language :: Python :: 3.13
Classifier: Typing :: Typed
Requires-Python: >=3.9
Requires-Dist: curl-cffi>=0.5.0
Requires-Dist: pydantic>=2.0.0
Requires-Dist: pyrogram>=2.0.0
Requires-Dist: tgcrypto>=1.2.0
